aiogram_tools/__init__.py
aiogram_tools/_bot.py
aiogram_tools/_currents.py
aiogram_tools/_inline_keyboard.py
aiogram_tools/_models.py
aiogram_tools/_questions.py
aiogram_tools/_states.py
aiogram_tools/context.py
aiogram_tools/deps.py
aiogram_tools/dispatcher.py
aiogram_tools/filters.py
aiogram_tools/keyboards.py
aiogram_tools/middlewares/__init__.py
aiogram_tools/middlewares/_conversation.py
aiogram_tools/middlewares/_membership.py
aiogram_tools/middlewares/misc.py
aiogram_tools/middlewares/throttling.py
aiogram_tools-1.0.1.dist-info/WHEEL
aiogram_tools-1.0.1.dist-info/METADATA
aiogram_tools-1.0.1.dist-info/RECORD
